[
    {
        "astCommandId": "live555:1:1",
        "astCommand": [
            "set",
            "-xe"
        ]
    },
    {
        "astCommandId": "live555:1:2",
        "astCommand": [
            "yum",
            "install",
            "-y",
            "compat-openssl10",
            "wget"
        ]
    },
    {
        "astCommandId": "live555:1:3",
        "astCommand": [
            "wget",
            "-qP",
            "/usr/local/bin/",
            "http://www.live555.com/mediaServer/linux/live555MediaServer"
        ]
    }
]