[
    {
        "astCommandId": "skype:2:0",
        "astCommand": {
            "children": [],
            "type": "SC-APT-GET-UPDATE"
        }
    },
    {
        "astCommandId": "skype:2:1",
        "astCommand": {
            "children": [
                {
                    "children": [],
                    "type": "SC-APT-GET-F-YES"
                },
                {
                    "children": [],
                    "type": "SC-APT-GET-F-NO-INSTALL-RECOMMENDS"
                },
                {
                    "children": [
                        {
                            "children": [],
                            "type": "SC-APT-GET-PACKAGE:APT-TRANSPORT-HTTPS"
                        },
                        {
                            "children": [],
                            "type": "SC-APT-GET-PACKAGE:CA-CERTIFICATES"
                        },
                        {
                            "children": [],
                            "type": "SC-APT-GET-PACKAGE:CURL"
                        },
                        {
                            "children": [],
                            "type": "SC-APT-GET-PACKAGE:GNUPG"
                        },
                        {
                            "children": [],
                            "type": "SC-APT-GET-PACKAGE:PROCPS"
                        }
                    ],
                    "type": "SC-APT-GET-PACKAGES"
                }
            ],
            "type": "SC-APT-GET-INSTALL"
        }
    },
    {
        "astCommandId": "skype:3:0",
        "astCommand": {
            "children": [
                {
                    "children": [],
                    "type": "SC-CURL-F-SILENT"
                },
                {
                    "children": [],
                    "type": "SC-CURL-F-SHOW-ERROR"
                },
                {
                    "children": [],
                    "type": "SC-CURL-F-LOCATION"
                },
                {
                    "children": [
                        {
                            "children": [
                                {
                                    "type": "ABS-URL-PROTOCOL-HTTPS",
                                    "children": []
                                },
                                {
                                    "type": "ABS-PROBABLY-URL",
                                    "children": []
                                }
                            ],
                            "type": "BASH-LITERAL"
                        }
                    ],
                    "type": "SC-CURL-URL"
                }
            ],
            "type": "SC-CURL"
        }
    },
    {
        "astCommandId": "skype:3:1",
        "astCommand": {
            "children": [
                {
                    "children": [],
                    "type": "SC-APT-KEY-FILENAME"
                }
            ],
            "type": "SC-APT-KEY-ADD"
        }
    },
    {
        "astCommandId": "skype:4:0",
        "astCommand": {
            "children": [
                {
                    "children": [
                        {
                            "children": [
                                {
                                    "children": [
                                        {
                                            "type": "ABS-URL-PROTOCOL-HTTPS",
                                            "children": []
                                        },
                                        {
                                            "type": "ABS-PROBABLY-URL",
                                            "children": []
                                        },
                                        {
                                            "type": "ABS-SINGLE-SPACE",
                                            "children": []
                                        }
                                    ],
                                    "type": "BASH-LITERAL"
                                }
                            ],
                            "type": "SC-ECHO-ITEM"
                        }
                    ],
                    "type": "SC-ECHO-ITEMS"
                }
            ],
            "type": "SC-ECHO"
        }
    },
    {
        "astCommandId": "skype:5:0",
        "astCommand": {
            "children": [],
            "type": "SC-APT-GET-UPDATE"
        }
    },
    {
        "astCommandId": "skype:5:1",
        "astCommand": {
            "children": [
                {
                    "children": [],
                    "type": "SC-APT-GET-F-YES"
                },
                {
                    "children": [],
                    "type": "SC-APT-GET-F-NO-INSTALL-RECOMMENDS"
                },
                {
                    "children": [
                        {
                            "children": [],
                            "type": "SC-APT-GET-PACKAGE:SKYPEFORLINUX"
                        }
                    ],
                    "type": "SC-APT-GET-PACKAGES"
                }
            ],
            "type": "SC-APT-GET-INSTALL"
        }
    },
    {
        "astCommandId": "skype:5:2",
        "astCommand": {
            "children": [
                {
                    "children": [],
                    "type": "SC-RM-F-RECURSIVE"
                },
                {
                    "children": [],
                    "type": "SC-RM-F-FORCE"
                },
                {
                    "children": [
                        {
                            "children": [
                                {
                                    "children": [
                                        {
                                            "children": [
                                                {
                                                    "type": "ABS-PATH-VAR",
                                                    "children": []
                                                },
                                                {
                                                    "type": "ABS-PATH-ABSOLUTE",
                                                    "children": []
                                                },
                                                {
                                                    "type": "ABS-APT-LISTS",
                                                    "children": []
                                                },
                                                {
                                                    "type": "ABS-MAYBE-PATH",
                                                    "children": []
                                                }
                                            ],
                                            "type": "BASH-LITERAL"
                                        },
                                        {
                                            "children": [
                                                {
                                                    "type": "ABS-GLOB-STAR",
                                                    "children": []
                                                }
                                            ],
                                            "type": "BASH-GLOB"
                                        }
                                    ],
                                    "type": "BASH-CONCAT"
                                }
                            ],
                            "type": "SC-RM-PATH"
                        }
                    ],
                    "type": "SC-RM-PATHS"
                }
            ],
            "type": "SC-RM"
        }
    },
    {
        "astCommandId": "skype:8:0",
        "astCommand": {
            "children": [
                {
                    "children": [],
                    "type": "SC-USER-ADD-F-CREATE-HOME"
                },
                {
                    "children": [
                        {
                            "children": [
                                {
                                    "children": [],
                                    "type": "BASH-VARIABLE:HOME"
                                }
                            ],
                            "type": "BASH-PATH"
                        }
                    ],
                    "type": "SC-USER-ADD-HOME-DIR"
                },
                {
                    "children": [
                        {
                            "children": [],
                            "type": "BASH-LITERAL"
                        }
                    ],
                    "type": "SC-USER-ADD-LOGIN"
                }
            ],
            "type": "SC-USER-ADD"
        }
    },
    {
        "astCommandId": "skype:8:1",
        "astCommand": {
            "children": [
                {
                    "children": [],
                    "type": "SC-CHOWN-F-RECURSIVE"
                },
                {
                    "children": [
                        {
                            "children": [],
                            "type": "BASH-LITERAL"
                        }
                    ],
                    "type": "SC-CHOWN-OWNER"
                },
                {
                    "children": [
                        {
                            "children": [
                                {
                                    "children": [],
                                    "type": "BASH-VARIABLE:HOME"
                                }
                            ],
                            "type": "SC-CHOWN-PATH"
                        }
                    ],
                    "type": "SC-CHOWN-PATHS"
                }
            ],
            "type": "SC-CHOWN"
        }
    }
]