[
    {
        "astCommandId": "f2353b5b9cddc3ace84dbabc27dfb4a98d7992d3:1:0",
        "astCommand": {
            "children": [
                {
                    "children": [
                        {
                            "children": [],
                            "type": "BASH-LITERAL",
                            "value": "i386"
                        }
                    ],
                    "type": "SC-DPKG-ADD-ARCHITECTURE"
                }
            ],
            "type": "SC-DPKG"
        }
    },
    {
        "astCommandId": "f2353b5b9cddc3ace84dbabc27dfb4a98d7992d3:2:0",
        "astCommand": {
            "children": [],
            "type": "SC-APT-GET-UPDATE"
        }
    },
    {
        "astCommandId": "f2353b5b9cddc3ace84dbabc27dfb4a98d7992d3:2:1",
        "astCommand": {
            "children": [
                {
                    "children": [],
                    "type": "SC-APT-GET-F-YES"
                },
                {
                    "children": [],
                    "type": "SC-APT-GET-F-NO-INSTALL-RECOMMENDS"
                },
                {
                    "children": [
                        {
                            "children": [
                                {
                                    "children": [],
                                    "type": "BASH-LITERAL",
                                    "value": "gcc"
                                }
                            ],
                            "type": "SC-APT-GET-PACKAGE"
                        },
                        {
                            "children": [
                                {
                                    "children": [],
                                    "type": "BASH-LITERAL",
                                    "value": "libc6-dev"
                                }
                            ],
                            "type": "SC-APT-GET-PACKAGE"
                        },
                        {
                            "children": [
                                {
                                    "children": [],
                                    "type": "BASH-LITERAL",
                                    "value": "make"
                                }
                            ],
                            "type": "SC-APT-GET-PACKAGE"
                        },
                        {
                            "children": [
                                {
                                    "children": [],
                                    "type": "BASH-LITERAL",
                                    "value": "libc6-dev:i386"
                                }
                            ],
                            "type": "SC-APT-GET-PACKAGE"
                        },
                        {
                            "children": [
                                {
                                    "children": [],
                                    "type": "BASH-LITERAL",
                                    "value": "libgcc-6-dev:i386"
                                }
                            ],
                            "type": "SC-APT-GET-PACKAGE"
                        },
                        {
                            "children": [
                                {
                                    "children": [],
                                    "type": "BASH-LITERAL",
                                    "value": "libc6-dev-arm64-cross"
                                }
                            ],
                            "type": "SC-APT-GET-PACKAGE"
                        },
                        {
                            "children": [
                                {
                                    "children": [],
                                    "type": "BASH-LITERAL",
                                    "value": "libc6-dev-armel-cross"
                                }
                            ],
                            "type": "SC-APT-GET-PACKAGE"
                        },
                        {
                            "children": [
                                {
                                    "children": [],
                                    "type": "BASH-LITERAL",
                                    "value": "libc6-dev-armhf-cross"
                                }
                            ],
                            "type": "SC-APT-GET-PACKAGE"
                        },
                        {
                            "children": [
                                {
                                    "children": [],
                                    "type": "BASH-LITERAL",
                                    "value": "libc6-dev-ppc64el-cross"
                                }
                            ],
                            "type": "SC-APT-GET-PACKAGE"
                        },
                        {
                            "children": [
                                {
                                    "children": [],
                                    "type": "BASH-LITERAL",
                                    "value": "libc6-dev-s390x-cross"
                                }
                            ],
                            "type": "SC-APT-GET-PACKAGE"
                        },
                        {
                            "children": [
                                {
                                    "children": [],
                                    "type": "BASH-LITERAL",
                                    "value": "gcc-aarch64-linux-gnu"
                                }
                            ],
                            "type": "SC-APT-GET-PACKAGE"
                        },
                        {
                            "children": [
                                {
                                    "children": [],
                                    "type": "BASH-LITERAL",
                                    "value": "gcc-arm-linux-gnueabi"
                                }
                            ],
                            "type": "SC-APT-GET-PACKAGE"
                        },
                        {
                            "children": [
                                {
                                    "children": [],
                                    "type": "BASH-LITERAL",
                                    "value": "gcc-arm-linux-gnueabihf"
                                }
                            ],
                            "type": "SC-APT-GET-PACKAGE"
                        },
                        {
                            "children": [
                                {
                                    "children": [],
                                    "type": "BASH-LITERAL",
                                    "value": "gcc-powerpc64le-linux-gnu"
                                }
                            ],
                            "type": "SC-APT-GET-PACKAGE"
                        },
                        {
                            "children": [
                                {
                                    "children": [],
                                    "type": "BASH-LITERAL",
                                    "value": "gcc-s390x-linux-gnu"
                                }
                            ],
                            "type": "SC-APT-GET-PACKAGE"
                        },
                        {
                            "children": [
                                {
                                    "children": [],
                                    "type": "BASH-LITERAL",
                                    "value": "file"
                                }
                            ],
                            "type": "SC-APT-GET-PACKAGE"
                        }
                    ],
                    "type": "SC-APT-GET-PACKAGES"
                }
            ],
            "type": "SC-APT-GET-INSTALL"
        }
    },
    {
        "astCommandId": "f2353b5b9cddc3ace84dbabc27dfb4a98d7992d3:2:2",
        "astCommand": {
            "children": [
                {
                    "children": [],
                    "type": "SC-RM-F-RECURSIVE"
                },
                {
                    "children": [],
                    "type": "SC-RM-F-FORCE"
                },
                {
                    "children": [
                        {
                            "children": [
                                {
                                    "children": [
                                        {
                                            "children": [],
                                            "type": "BASH-LITERAL",
                                            "value": "/var/lib/apt/lists/"
                                        },
                                        {
                                            "children": [],
                                            "type": "BASH-GLOB",
                                            "value": "*"
                                        }
                                    ],
                                    "type": "BASH-CONCAT"
                                }
                            ],
                            "type": "SC-RM-PATH"
                        }
                    ],
                    "type": "SC-RM-PATHS"
                }
            ],
            "type": "SC-RM"
        }
    },
    {
        "astCommandId": "f2353b5b9cddc3ace84dbabc27dfb4a98d7992d3:5:0",
        "astCommand": {
            "children": [
                {
                    "children": [],
                    "type": "SC-SET-F-E"
                },
                {
                    "children": [],
                    "type": "SC-SET-F-X"
                }
            ],
            "type": "SC-SET"
        }
    },
    {
        "astCommandId": "f2353b5b9cddc3ace84dbabc27dfb4a98d7992d3:5:1",
        "astCommand": {
            "children": [
                {
                    "children": [
                        {
                            "children": [],
                            "type": "BASH-LITERAL",
                            "value": "clean"
                        }
                    ],
                    "type": "SC-MAKE-TARGET"
                },
                {
                    "children": [
                        {
                            "children": [
                                {
                                    "children": [],
                                    "type": "BASH-LITERAL",
                                    "value": "all"
                                }
                            ],
                            "type": "SC-MAKE-ARG"
                        },
                        {
                            "children": [
                                {
                                    "children": [],
                                    "type": "BASH-LITERAL",
                                    "value": "test"
                                }
                            ],
                            "type": "SC-MAKE-ARG"
                        },
                        {
                            "children": [
                                {
                                    "children": [
                                        {
                                            "children": [],
                                            "type": "BASH-LITERAL",
                                            "value": "TARGET_ARCH="
                                        },
                                        {
                                            "children": [],
                                            "type": "BASH-SINGLE-QUOTED",
                                            "value": "amd64"
                                        }
                                    ],
                                    "type": "BASH-CONCAT"
                                }
                            ],
                            "type": "SC-MAKE-ARG"
                        },
                        {
                            "children": [
                                {
                                    "children": [
                                        {
                                            "children": [],
                                            "type": "BASH-LITERAL",
                                            "value": "CC="
                                        },
                                        {
                                            "children": [],
                                            "type": "BASH-SINGLE-QUOTED",
                                            "value": "x86_64-linux-gnu-gcc"
                                        }
                                    ],
                                    "type": "BASH-CONCAT"
                                }
                            ],
                            "type": "SC-MAKE-ARG"
                        },
                        {
                            "children": [
                                {
                                    "children": [
                                        {
                                            "children": [],
                                            "type": "BASH-LITERAL",
                                            "value": "STRIP="
                                        },
                                        {
                                            "children": [],
                                            "type": "BASH-SINGLE-QUOTED",
                                            "value": "x86_64-linux-gnu-strip"
                                        }
                                    ],
                                    "type": "BASH-CONCAT"
                                }
                            ],
                            "type": "SC-MAKE-ARG"
                        }
                    ],
                    "type": "SC-MAKE-ARGS"
                }
            ],
            "type": "SC-MAKE"
        }
    },
    {
        "astCommandId": "f2353b5b9cddc3ace84dbabc27dfb4a98d7992d3:6:0",
        "astCommand": {
            "children": [
                {
                    "children": [],
                    "type": "SC-SET-F-E"
                },
                {
                    "children": [],
                    "type": "SC-SET-F-X"
                }
            ],
            "type": "SC-SET"
        }
    },
    {
        "astCommandId": "f2353b5b9cddc3ace84dbabc27dfb4a98d7992d3:6:1",
        "astCommand": {
            "children": [
                {
                    "children": [
                        {
                            "children": [],
                            "type": "BASH-LITERAL",
                            "value": "clean"
                        }
                    ],
                    "type": "SC-MAKE-TARGET"
                },
                {
                    "children": [
                        {
                            "children": [
                                {
                                    "children": [],
                                    "type": "BASH-LITERAL",
                                    "value": "all"
                                }
                            ],
                            "type": "SC-MAKE-ARG"
                        },
                        {
                            "children": [
                                {
                                    "children": [
                                        {
                                            "children": [],
                                            "type": "BASH-LITERAL",
                                            "value": "TARGET_ARCH="
                                        },
                                        {
                                            "children": [],
                                            "type": "BASH-SINGLE-QUOTED",
                                            "value": "arm32v5"
                                        }
                                    ],
                                    "type": "BASH-CONCAT"
                                }
                            ],
                            "type": "SC-MAKE-ARG"
                        },
                        {
                            "children": [
                                {
                                    "children": [
                                        {
                                            "children": [],
                                            "type": "BASH-LITERAL",
                                            "value": "CC="
                                        },
                                        {
                                            "children": [],
                                            "type": "BASH-SINGLE-QUOTED",
                                            "value": "arm-linux-gnueabi-gcc"
                                        }
                                    ],
                                    "type": "BASH-CONCAT"
                                }
                            ],
                            "type": "SC-MAKE-ARG"
                        },
                        {
                            "children": [
                                {
                                    "children": [
                                        {
                                            "children": [],
                                            "type": "BASH-LITERAL",
                                            "value": "STRIP="
                                        },
                                        {
                                            "children": [],
                                            "type": "BASH-SINGLE-QUOTED",
                                            "value": "arm-linux-gnueabi-strip"
                                        }
                                    ],
                                    "type": "BASH-CONCAT"
                                }
                            ],
                            "type": "SC-MAKE-ARG"
                        }
                    ],
                    "type": "SC-MAKE-ARGS"
                }
            ],
            "type": "SC-MAKE"
        }
    },
    {
        "astCommandId": "f2353b5b9cddc3ace84dbabc27dfb4a98d7992d3:7:0",
        "astCommand": {
            "children": [
                {
                    "children": [],
                    "type": "SC-SET-F-E"
                },
                {
                    "children": [],
                    "type": "SC-SET-F-X"
                }
            ],
            "type": "SC-SET"
        }
    },
    {
        "astCommandId": "f2353b5b9cddc3ace84dbabc27dfb4a98d7992d3:7:1",
        "astCommand": {
            "children": [
                {
                    "children": [
                        {
                            "children": [],
                            "type": "BASH-LITERAL",
                            "value": "clean"
                        }
                    ],
                    "type": "SC-MAKE-TARGET"
                },
                {
                    "children": [
                        {
                            "children": [
                                {
                                    "children": [],
                                    "type": "BASH-LITERAL",
                                    "value": "all"
                                }
                            ],
                            "type": "SC-MAKE-ARG"
                        },
                        {
                            "children": [
                                {
                                    "children": [
                                        {
                                            "children": [],
                                            "type": "BASH-LITERAL",
                                            "value": "TARGET_ARCH="
                                        },
                                        {
                                            "children": [],
                                            "type": "BASH-SINGLE-QUOTED",
                                            "value": "arm32v7"
                                        }
                                    ],
                                    "type": "BASH-CONCAT"
                                }
                            ],
                            "type": "SC-MAKE-ARG"
                        },
                        {
                            "children": [
                                {
                                    "children": [
                                        {
                                            "children": [],
                                            "type": "BASH-LITERAL",
                                            "value": "CC="
                                        },
                                        {
                                            "children": [],
                                            "type": "BASH-SINGLE-QUOTED",
                                            "value": "arm-linux-gnueabihf-gcc"
                                        }
                                    ],
                                    "type": "BASH-CONCAT"
                                }
                            ],
                            "type": "SC-MAKE-ARG"
                        },
                        {
                            "children": [
                                {
                                    "children": [
                                        {
                                            "children": [],
                                            "type": "BASH-LITERAL",
                                            "value": "STRIP="
                                        },
                                        {
                                            "children": [],
                                            "type": "BASH-SINGLE-QUOTED",
                                            "value": "arm-linux-gnueabihf-strip"
                                        }
                                    ],
                                    "type": "BASH-CONCAT"
                                }
                            ],
                            "type": "SC-MAKE-ARG"
                        }
                    ],
                    "type": "SC-MAKE-ARGS"
                }
            ],
            "type": "SC-MAKE"
        }
    },
    {
        "astCommandId": "f2353b5b9cddc3ace84dbabc27dfb4a98d7992d3:8:0",
        "astCommand": {
            "children": [
                {
                    "children": [],
                    "type": "SC-SET-F-E"
                },
                {
                    "children": [],
                    "type": "SC-SET-F-X"
                }
            ],
            "type": "SC-SET"
        }
    },
    {
        "astCommandId": "f2353b5b9cddc3ace84dbabc27dfb4a98d7992d3:8:1",
        "astCommand": {
            "children": [
                {
                    "children": [
                        {
                            "children": [],
                            "type": "BASH-LITERAL",
                            "value": "clean"
                        }
                    ],
                    "type": "SC-MAKE-TARGET"
                },
                {
                    "children": [
                        {
                            "children": [
                                {
                                    "children": [],
                                    "type": "BASH-LITERAL",
                                    "value": "all"
                                }
                            ],
                            "type": "SC-MAKE-ARG"
                        },
                        {
                            "children": [
                                {
                                    "children": [
                                        {
                                            "children": [],
                                            "type": "BASH-LITERAL",
                                            "value": "TARGET_ARCH="
                                        },
                                        {
                                            "children": [],
                                            "type": "BASH-SINGLE-QUOTED",
                                            "value": "arm64v8"
                                        }
                                    ],
                                    "type": "BASH-CONCAT"
                                }
                            ],
                            "type": "SC-MAKE-ARG"
                        },
                        {
                            "children": [
                                {
                                    "children": [
                                        {
                                            "children": [],
                                            "type": "BASH-LITERAL",
                                            "value": "CC="
                                        },
                                        {
                                            "children": [],
                                            "type": "BASH-SINGLE-QUOTED",
                                            "value": "aarch64-linux-gnu-gcc"
                                        }
                                    ],
                                    "type": "BASH-CONCAT"
                                }
                            ],
                            "type": "SC-MAKE-ARG"
                        },
                        {
                            "children": [
                                {
                                    "children": [
                                        {
                                            "children": [],
                                            "type": "BASH-LITERAL",
                                            "value": "STRIP="
                                        },
                                        {
                                            "children": [],
                                            "type": "BASH-SINGLE-QUOTED",
                                            "value": "aarch64-linux-gnu-strip"
                                        }
                                    ],
                                    "type": "BASH-CONCAT"
                                }
                            ],
                            "type": "SC-MAKE-ARG"
                        }
                    ],
                    "type": "SC-MAKE-ARGS"
                }
            ],
            "type": "SC-MAKE"
        }
    },
    {
        "astCommandId": "f2353b5b9cddc3ace84dbabc27dfb4a98d7992d3:9:0",
        "astCommand": {
            "children": [
                {
                    "children": [],
                    "type": "SC-SET-F-E"
                },
                {
                    "children": [],
                    "type": "SC-SET-F-X"
                }
            ],
            "type": "SC-SET"
        }
    },
    {
        "astCommandId": "f2353b5b9cddc3ace84dbabc27dfb4a98d7992d3:9:1",
        "astCommand": {
            "children": [
                {
                    "children": [
                        {
                            "children": [],
                            "type": "BASH-LITERAL",
                            "value": "clean"
                        }
                    ],
                    "type": "SC-MAKE-TARGET"
                },
                {
                    "children": [
                        {
                            "children": [
                                {
                                    "children": [],
                                    "type": "BASH-LITERAL",
                                    "value": "all"
                                }
                            ],
                            "type": "SC-MAKE-ARG"
                        },
                        {
                            "children": [
                                {
                                    "children": [],
                                    "type": "BASH-LITERAL",
                                    "value": "test"
                                }
                            ],
                            "type": "SC-MAKE-ARG"
                        },
                        {
                            "children": [
                                {
                                    "children": [
                                        {
                                            "children": [],
                                            "type": "BASH-LITERAL",
                                            "value": "TARGET_ARCH="
                                        },
                                        {
                                            "children": [],
                                            "type": "BASH-SINGLE-QUOTED",
                                            "value": "i386"
                                        }
                                    ],
                                    "type": "BASH-CONCAT"
                                }
                            ],
                            "type": "SC-MAKE-ARG"
                        },
                        {
                            "children": [
                                {
                                    "children": [
                                        {
                                            "children": [],
                                            "type": "BASH-LITERAL",
                                            "value": "CC="
                                        },
                                        {
                                            "children": [],
                                            "type": "BASH-SINGLE-QUOTED",
                                            "value": "gcc -m32 -L/usr/lib/gcc/i686-linux-gnu/6"
                                        }
                                    ],
                                    "type": "BASH-CONCAT"
                                }
                            ],
                            "type": "SC-MAKE-ARG"
                        },
                        {
                            "children": [
                                {
                                    "children": [
                                        {
                                            "children": [],
                                            "type": "BASH-LITERAL",
                                            "value": "STRIP="
                                        },
                                        {
                                            "children": [],
                                            "type": "BASH-SINGLE-QUOTED",
                                            "value": "x86_64-linux-gnu-strip"
                                        }
                                    ],
                                    "type": "BASH-CONCAT"
                                }
                            ],
                            "type": "SC-MAKE-ARG"
                        }
                    ],
                    "type": "SC-MAKE-ARGS"
                }
            ],
            "type": "SC-MAKE"
        }
    },
    {
        "astCommandId": "f2353b5b9cddc3ace84dbabc27dfb4a98d7992d3:10:0",
        "astCommand": {
            "children": [
                {
                    "children": [],
                    "type": "SC-SET-F-E"
                },
                {
                    "children": [],
                    "type": "SC-SET-F-X"
                }
            ],
            "type": "SC-SET"
        }
    },
    {
        "astCommandId": "f2353b5b9cddc3ace84dbabc27dfb4a98d7992d3:10:1",
        "astCommand": {
            "children": [
                {
                    "children": [
                        {
                            "children": [],
                            "type": "BASH-LITERAL",
                            "value": "clean"
                        }
                    ],
                    "type": "SC-MAKE-TARGET"
                },
                {
                    "children": [
                        {
                            "children": [
                                {
                                    "children": [],
                                    "type": "BASH-LITERAL",
                                    "value": "all"
                                }
                            ],
                            "type": "SC-MAKE-ARG"
                        },
                        {
                            "children": [
                                {
                                    "children": [
                                        {
                                            "children": [],
                                            "type": "BASH-LITERAL",
                                            "value": "TARGET_ARCH="
                                        },
                                        {
                                            "children": [],
                                            "type": "BASH-SINGLE-QUOTED",
                                            "value": "ppc64le"
                                        }
                                    ],
                                    "type": "BASH-CONCAT"
                                }
                            ],
                            "type": "SC-MAKE-ARG"
                        },
                        {
                            "children": [
                                {
                                    "children": [
                                        {
                                            "children": [],
                                            "type": "BASH-LITERAL",
                                            "value": "CC="
                                        },
                                        {
                                            "children": [],
                                            "type": "BASH-SINGLE-QUOTED",
                                            "value": "powerpc64le-linux-gnu-gcc"
                                        }
                                    ],
                                    "type": "BASH-CONCAT"
                                }
                            ],
                            "type": "SC-MAKE-ARG"
                        },
                        {
                            "children": [
                                {
                                    "children": [
                                        {
                                            "children": [],
                                            "type": "BASH-LITERAL",
                                            "value": "STRIP="
                                        },
                                        {
                                            "children": [],
                                            "type": "BASH-SINGLE-QUOTED",
                                            "value": "powerpc64le-linux-gnu-strip"
                                        }
                                    ],
                                    "type": "BASH-CONCAT"
                                }
                            ],
                            "type": "SC-MAKE-ARG"
                        }
                    ],
                    "type": "SC-MAKE-ARGS"
                }
            ],
            "type": "SC-MAKE"
        }
    },
    {
        "astCommandId": "f2353b5b9cddc3ace84dbabc27dfb4a98d7992d3:11:0",
        "astCommand": {
            "children": [
                {
                    "children": [],
                    "type": "SC-SET-F-E"
                },
                {
                    "children": [],
                    "type": "SC-SET-F-X"
                }
            ],
            "type": "SC-SET"
        }
    },
    {
        "astCommandId": "f2353b5b9cddc3ace84dbabc27dfb4a98d7992d3:11:1",
        "astCommand": {
            "children": [
                {
                    "children": [
                        {
                            "children": [],
                            "type": "BASH-LITERAL",
                            "value": "clean"
                        }
                    ],
                    "type": "SC-MAKE-TARGET"
                },
                {
                    "children": [
                        {
                            "children": [
                                {
                                    "children": [],
                                    "type": "BASH-LITERAL",
                                    "value": "all"
                                }
                            ],
                            "type": "SC-MAKE-ARG"
                        },
                        {
                            "children": [
                                {
                                    "children": [
                                        {
                                            "children": [],
                                            "type": "BASH-LITERAL",
                                            "value": "TARGET_ARCH="
                                        },
                                        {
                                            "children": [],
                                            "type": "BASH-SINGLE-QUOTED",
                                            "value": "s390x"
                                        }
                                    ],
                                    "type": "BASH-CONCAT"
                                }
                            ],
                            "type": "SC-MAKE-ARG"
                        },
                        {
                            "children": [
                                {
                                    "children": [
                                        {
                                            "children": [],
                                            "type": "BASH-LITERAL",
                                            "value": "CC="
                                        },
                                        {
                                            "children": [],
                                            "type": "BASH-SINGLE-QUOTED",
                                            "value": "s390x-linux-gnu-gcc"
                                        }
                                    ],
                                    "type": "BASH-CONCAT"
                                }
                            ],
                            "type": "SC-MAKE-ARG"
                        },
                        {
                            "children": [
                                {
                                    "children": [
                                        {
                                            "children": [],
                                            "type": "BASH-LITERAL",
                                            "value": "STRIP="
                                        },
                                        {
                                            "children": [],
                                            "type": "BASH-SINGLE-QUOTED",
                                            "value": "s390x-linux-gnu-strip"
                                        }
                                    ],
                                    "type": "BASH-CONCAT"
                                }
                            ],
                            "type": "SC-MAKE-ARG"
                        }
                    ],
                    "type": "SC-MAKE-ARGS"
                }
            ],
            "type": "SC-MAKE"
        }
    }
]