[
    {
        "astCommandId": "027de8dd9fb86c52209cb18af272ab6958a5eae5:4:0",
        "astCommand": {
            "children": [],
            "type": "SC-APT-GET-UPDATE"
        }
    },
    {
        "astCommandId": "027de8dd9fb86c52209cb18af272ab6958a5eae5:4:1",
        "astCommand": {
            "children": [
                {
                    "children": [],
                    "type": "SC-APT-GET-F-YES"
                },
                {
                    "children": [],
                    "type": "SC-APT-GET-F-NO-INSTALL-RECOMMENDS"
                },
                {
                    "children": [
                        {
                            "children": [],
                            "type": "SC-APT-GET-PACKAGE:TK-DEV"
                        }
                    ],
                    "type": "SC-APT-GET-PACKAGES"
                }
            ],
            "type": "SC-APT-GET-INSTALL"
        }
    },
    {
        "astCommandId": "027de8dd9fb86c52209cb18af272ab6958a5eae5:4:2",
        "astCommand": {
            "children": [
                {
                    "children": [],
                    "type": "SC-RM-F-RECURSIVE"
                },
                {
                    "children": [],
                    "type": "SC-RM-F-FORCE"
                },
                {
                    "children": [
                        {
                            "children": [
                                {
                                    "children": [
                                        {
                                            "children": [
                                                {
                                                    "type": "ABS-MAYBE-PATH",
                                                    "children": []
                                                },
                                                {
                                                    "type": "ABS-APT-LISTS",
                                                    "children": []
                                                },
                                                {
                                                    "type": "ABS-PATH-VAR",
                                                    "children": []
                                                },
                                                {
                                                    "type": "ABS-PATH-ABSOLUTE",
                                                    "children": []
                                                }
                                            ],
                                            "type": "BASH-LITERAL"
                                        },
                                        {
                                            "children": [
                                                {
                                                    "type": "ABS-GLOB-STAR",
                                                    "children": []
                                                }
                                            ],
                                            "type": "BASH-GLOB"
                                        }
                                    ],
                                    "type": "BASH-CONCAT"
                                }
                            ],
                            "type": "SC-RM-PATH"
                        }
                    ],
                    "type": "SC-RM-PATHS"
                }
            ],
            "type": "SC-RM"
        }
    },
    {
        "astCommandId": "027de8dd9fb86c52209cb18af272ab6958a5eae5:7:0",
        "astCommand": {
            "children": [
                {
                    "children": [],
                    "type": "SC-SET-F-E"
                },
                {
                    "children": [],
                    "type": "SC-SET-F-X"
                }
            ],
            "type": "SC-SET"
        }
    },
    {
        "astCommandId": "027de8dd9fb86c52209cb18af272ab6958a5eae5:7:1",
        "astCommand": {
            "children": [
                {
                    "children": [
                        {
                            "children": [
                                {
                                    "children": [
                                        {
                                            "type": "ABS-EXTENSION-TAR",
                                            "children": []
                                        }
                                    ],
                                    "type": "BASH-LITERAL"
                                }
                            ],
                            "type": "BASH-PATH"
                        }
                    ],
                    "type": "SC-WGET-OUTPUT-DOCUMENT"
                },
                {
                    "children": [
                        {
                            "children": [
                                {
                                    "type": "ABS-PROBABLY-URL",
                                    "children": []
                                },
                                {
                                    "type": "ABS-URL-PROTOCOL-HTTPS",
                                    "children": []
                                },
                                {
                                    "type": "ABS-EXTENSION-TAR",
                                    "children": []
                                }
                            ],
                            "type": "BASH-LITERAL"
                        }
                    ],
                    "type": "SC-WGET-URL"
                }
            ],
            "type": "SC-WGET"
        }
    },
    {
        "astCommandId": "027de8dd9fb86c52209cb18af272ab6958a5eae5:7:2",
        "astCommand": {
            "children": [
                {
                    "children": [
                        {
                            "children": [
                                {
                                    "children": [
                                        {
                                            "type": "ABS-EXTENSION-ASC",
                                            "children": []
                                        },
                                        {
                                            "type": "ABS-EXTENSION-TAR",
                                            "children": []
                                        }
                                    ],
                                    "type": "BASH-LITERAL"
                                }
                            ],
                            "type": "BASH-PATH"
                        }
                    ],
                    "type": "SC-WGET-OUTPUT-DOCUMENT"
                },
                {
                    "children": [
                        {
                            "children": [
                                {
                                    "type": "ABS-PROBABLY-URL",
                                    "children": []
                                },
                                {
                                    "type": "ABS-URL-PROTOCOL-HTTPS",
                                    "children": []
                                },
                                {
                                    "type": "ABS-EXTENSION-ASC",
                                    "children": []
                                },
                                {
                                    "type": "ABS-EXTENSION-TAR",
                                    "children": []
                                }
                            ],
                            "type": "BASH-LITERAL"
                        }
                    ],
                    "type": "SC-WGET-URL"
                }
            ],
            "type": "SC-WGET"
        }
    },
    {
        "astCommandId": "027de8dd9fb86c52209cb18af272ab6958a5eae5:7:3",
        "astCommand": {
            "children": [
                {
                    "children": [
                        {
                            "children": [
                                {
                                    "children": [
                                        {
                                            "children": [],
                                            "type": "BASH-VARIABLE:GNUPGHOME"
                                        }
                                    ],
                                    "type": "BASH-ASSIGN-LHS"
                                },
                                {
                                    "children": [
                                        {
                                            "children": [
                                                {
                                                    "children": [
                                                        {
                                                            "children": [
                                                                {
                                                                    "children": [],
                                                                    "type": "SC-MKTEMP-F-DIRECTORY"
                                                                }
                                                            ],
                                                            "type": "SC-MKTEMP"
                                                        }
                                                    ],
                                                    "type": "BASH-DOLLAR-PARENS"
                                                }
                                            ],
                                            "type": "BASH-DOUBLE-QUOTED"
                                        }
                                    ],
                                    "type": "BASH-ASSIGN-RHS"
                                }
                            ],
                            "type": "BASH-ASSIGN"
                        }
                    ],
                    "type": "SC-EXPORT-TARGET"
                }
            ],
            "type": "SC-EXPORT"
        }
    },
    {
        "astCommandId": "027de8dd9fb86c52209cb18af272ab6958a5eae5:7:4",
        "astCommand": {
            "children": [
                {
                    "children": [],
                    "type": "SC-GPG-F-BATCH"
                },
                {
                    "children": [
                        {
                            "children": [
                                {
                                    "type": "ABS-PROBABLY-URL",
                                    "children": []
                                },
                                {
                                    "type": "ABS-URL-HA-POOL",
                                    "children": []
                                },
                                {
                                    "type": "ABS-URL-POOL",
                                    "children": []
                                }
                            ],
                            "type": "BASH-LITERAL"
                        }
                    ],
                    "type": "SC-GPG-KEYSERVER"
                },
                {
                    "children": [
                        {
                            "children": [
                                {
                                    "children": [],
                                    "type": "BASH-LITERAL"
                                }
                            ],
                            "type": "SC-GPG-RECV-KEY"
                        }
                    ],
                    "type": "SC-GPG-RECV-KEYS"
                }
            ],
            "type": "SC-GPG"
        }
    },
    {
        "astCommandId": "027de8dd9fb86c52209cb18af272ab6958a5eae5:7:5",
        "astCommand": {
            "children": [
                {
                    "children": [],
                    "type": "SC-GPG-F-BATCH"
                },
                {
                    "children": [
                        {
                            "children": [
                                {
                                    "children": [
                                        {
                                            "type": "ABS-EXTENSION-ASC",
                                            "children": []
                                        },
                                        {
                                            "type": "ABS-EXTENSION-TAR",
                                            "children": []
                                        }
                                    ],
                                    "type": "BASH-LITERAL"
                                }
                            ],
                            "type": "SC-GPG-VERIFY"
                        },
                        {
                            "children": [
                                {
                                    "children": [
                                        {
                                            "type": "ABS-EXTENSION-TAR",
                                            "children": []
                                        }
                                    ],
                                    "type": "BASH-LITERAL"
                                }
                            ],
                            "type": "SC-GPG-VERIFY"
                        }
                    ],
                    "type": "SC-GPG-VERIFYS"
                }
            ],
            "type": "SC-GPG"
        }
    },
    {
        "astCommandId": "027de8dd9fb86c52209cb18af272ab6958a5eae5:7:6",
        "astCommand": {
            "children": [],
            "type": "SC-TRUE"
        }
    },
    {
        "astCommandId": "027de8dd9fb86c52209cb18af272ab6958a5eae5:7:7",
        "astCommand": {
            "children": [
                {
                    "children": [],
                    "type": "SC-RM-F-RECURSIVE"
                },
                {
                    "children": [],
                    "type": "SC-RM-F-FORCE"
                },
                {
                    "children": [
                        {
                            "children": [
                                {
                                    "children": [],
                                    "type": "BASH-LITERAL"
                                }
                            ],
                            "type": "SC-RM-PATH"
                        },
                        {
                            "children": [
                                {
                                    "children": [
                                        {
                                            "type": "ABS-EXTENSION-ASC",
                                            "children": []
                                        },
                                        {
                                            "type": "ABS-EXTENSION-TAR",
                                            "children": []
                                        }
                                    ],
                                    "type": "BASH-LITERAL"
                                }
                            ],
                            "type": "SC-RM-PATH"
                        }
                    ],
                    "type": "SC-RM-PATHS"
                }
            ],
            "type": "SC-RM"
        }
    },
    {
        "astCommandId": "027de8dd9fb86c52209cb18af272ab6958a5eae5:7:8",
        "astCommand": {
            "children": [
                {
                    "children": [],
                    "type": "SC-MKDIR-F-PARENTS"
                },
                {
                    "children": [
                        {
                            "children": [
                                {
                                    "children": [
                                        {
                                            "type": "ABS-MAYBE-PATH",
                                            "children": []
                                        },
                                        {
                                            "type": "ABS-PATH-ABSOLUTE",
                                            "children": []
                                        },
                                        {
                                            "type": "ABS-MAYBE-SRC-DIR",
                                            "children": []
                                        },
                                        {
                                            "type": "ABS-USR-SRC-DIR",
                                            "children": []
                                        }
                                    ],
                                    "type": "BASH-LITERAL"
                                }
                            ],
                            "type": "SC-MKDIR-PATH"
                        }
                    ],
                    "type": "SC-MKDIR-PATHS"
                }
            ],
            "type": "SC-MKDIR"
        }
    },
    {
        "astCommandId": "027de8dd9fb86c52209cb18af272ab6958a5eae5:7:9",
        "astCommand": {
            "children": [
                {
                    "children": [],
                    "type": "SC-TAR-X"
                },
                {
                    "children": [],
                    "type": "SC-TAR-J"
                },
                {
                    "children": [
                        {
                            "children": [
                                {
                                    "children": [
                                        {
                                            "type": "ABS-MAYBE-PATH",
                                            "children": []
                                        },
                                        {
                                            "type": "ABS-PATH-ABSOLUTE",
                                            "children": []
                                        },
                                        {
                                            "type": "ABS-MAYBE-SRC-DIR",
                                            "children": []
                                        },
                                        {
                                            "type": "ABS-USR-SRC-DIR",
                                            "children": []
                                        }
                                    ],
                                    "type": "BASH-LITERAL"
                                }
                            ],
                            "type": "BASH-PATH"
                        }
                    ],
                    "type": "SC-TAR-DIRECTORY"
                },
                {
                    "children": [
                        {
                            "children": [],
                            "type": "BASH-LITERAL"
                        }
                    ],
                    "type": "SC-TAR-STRIP-COMPONENTS"
                },
                {
                    "children": [
                        {
                            "children": [
                                {
                                    "children": [
                                        {
                                            "type": "ABS-EXTENSION-TAR",
                                            "children": []
                                        }
                                    ],
                                    "type": "BASH-LITERAL"
                                }
                            ],
                            "type": "BASH-PATH"
                        }
                    ],
                    "type": "SC-TAR-FILE"
                }
            ],
            "type": "SC-TAR"
        }
    },
    {
        "astCommandId": "027de8dd9fb86c52209cb18af272ab6958a5eae5:7:10",
        "astCommand": {
            "children": [
                {
                    "children": [
                        {
                            "children": [
                                {
                                    "children": [
                                        {
                                            "type": "ABS-EXTENSION-TAR",
                                            "children": []
                                        }
                                    ],
                                    "type": "BASH-LITERAL"
                                }
                            ],
                            "type": "SC-RM-PATH"
                        }
                    ],
                    "type": "SC-RM-PATHS"
                }
            ],
            "type": "SC-RM"
        }
    },
    {
        "astCommandId": "027de8dd9fb86c52209cb18af272ab6958a5eae5:7:11",
        "astCommand": {
            "children": [
                {
                    "children": [
                        {
                            "children": [
                                {
                                    "type": "ABS-MAYBE-PATH",
                                    "children": []
                                },
                                {
                                    "type": "ABS-PATH-ABSOLUTE",
                                    "children": []
                                },
                                {
                                    "type": "ABS-MAYBE-SRC-DIR",
                                    "children": []
                                },
                                {
                                    "type": "ABS-USR-SRC-DIR",
                                    "children": []
                                }
                            ],
                            "type": "BASH-LITERAL"
                        }
                    ],
                    "type": "SC-CD-PATH"
                }
            ],
            "type": "SC-CD"
        }
    },
    {
        "astCommandId": "027de8dd9fb86c52209cb18af272ab6958a5eae5:7:12",
        "astCommand": {
            "children": [
                {
                    "children": [
                        {
                            "children": [],
                            "type": "BASH-LITERAL"
                        }
                    ],
                    "type": "SC-DPKG-ARCHITECTURE-QUERY"
                }
            ],
            "type": "SC-DPKG-ARCHITECTURE"
        }
    },
    {
        "astCommandId": "027de8dd9fb86c52209cb18af272ab6958a5eae5:7:13",
        "astCommand": {
            "children": [
                {
                    "children": [
                        {
                            "children": [],
                            "type": "BASH-LITERAL"
                        }
                    ],
                    "type": "SC-CONFIGURE-BUILD"
                },
                {
                    "children": [],
                    "type": "SC-CONFIGURE-ENABLE-SHARED"
                },
                {
                    "children": [
                        {
                            "children": [],
                            "type": "BASH-LITERAL"
                        }
                    ],
                    "type": "SC-CONFIGURE-ENABLE-UNICODE"
                }
            ],
            "type": "SC-CONFIGURE"
        }
    },
    {
        "astCommandId": "027de8dd9fb86c52209cb18af272ab6958a5eae5:7:14",
        "astCommand": {
            "children": [
                {
                    "children": [
                        {
                            "children": [
                                {
                                    "type": "ABS-SINGLE-SPACE",
                                    "children": []
                                }
                            ],
                            "type": "BASH-LITERAL"
                        }
                    ],
                    "type": "SC-MAKE-JOBS"
                }
            ],
            "type": "SC-MAKE"
        }
    },
    {
        "astCommandId": "027de8dd9fb86c52209cb18af272ab6958a5eae5:7:15",
        "astCommand": {
            "children": [
                {
                    "children": [
                        {
                            "children": [],
                            "type": "BASH-LITERAL"
                        }
                    ],
                    "type": "SC-MAKE-TARGET"
                }
            ],
            "type": "SC-MAKE"
        }
    },
    {
        "astCommandId": "027de8dd9fb86c52209cb18af272ab6958a5eae5:7:16",
        "astCommand": {
            "children": [],
            "type": "SC-LDCONFIG"
        }
    },
    {
        "astCommandId": "027de8dd9fb86c52209cb18af272ab6958a5eae5:7:17",
        "astCommand": {
            "children": [
                {
                    "children": [],
                    "type": "SC-RM-F-RECURSIVE"
                },
                {
                    "children": [],
                    "type": "SC-RM-F-FORCE"
                },
                {
                    "children": [
                        {
                            "children": [
                                {
                                    "children": [
                                        {
                                            "type": "ABS-MAYBE-PATH",
                                            "children": []
                                        },
                                        {
                                            "type": "ABS-PATH-ABSOLUTE",
                                            "children": []
                                        },
                                        {
                                            "type": "ABS-MAYBE-SRC-DIR",
                                            "children": []
                                        },
                                        {
                                            "type": "ABS-USR-SRC-DIR",
                                            "children": []
                                        }
                                    ],
                                    "type": "BASH-LITERAL"
                                }
                            ],
                            "type": "SC-RM-PATH"
                        }
                    ],
                    "type": "SC-RM-PATHS"
                }
            ],
            "type": "SC-RM"
        }
    },
    {
        "astCommandId": "027de8dd9fb86c52209cb18af272ab6958a5eae5:7:18",
        "astCommand": {
            "children": [
                {
                    "children": [],
                    "type": "SC-PYTHON-F-VERSION"
                }
            ],
            "type": "SC-PYTHON"
        }
    },
    {
        "astCommandId": "027de8dd9fb86c52209cb18af272ab6958a5eae5:9:0",
        "astCommand": {
            "children": [
                {
                    "children": [],
                    "type": "SC-SET-F-E"
                },
                {
                    "children": [],
                    "type": "SC-SET-F-X"
                }
            ],
            "type": "SC-SET"
        }
    },
    {
        "astCommandId": "027de8dd9fb86c52209cb18af272ab6958a5eae5:9:1",
        "astCommand": {
            "children": [
                {
                    "children": [
                        {
                            "children": [
                                {
                                    "children": [
                                        {
                                            "type": "ABS-PROBABLY-URL",
                                            "children": []
                                        }
                                    ],
                                    "type": "BASH-LITERAL"
                                }
                            ],
                            "type": "BASH-PATH"
                        }
                    ],
                    "type": "SC-WGET-OUTPUT-DOCUMENT"
                },
                {
                    "children": [
                        {
                            "children": [
                                {
                                    "type": "ABS-PROBABLY-URL",
                                    "children": []
                                },
                                {
                                    "type": "ABS-URL-PROTOCOL-HTTPS",
                                    "children": []
                                }
                            ],
                            "type": "BASH-LITERAL"
                        }
                    ],
                    "type": "SC-WGET-URL"
                }
            ],
            "type": "SC-WGET"
        }
    },
    {
        "astCommandId": "027de8dd9fb86c52209cb18af272ab6958a5eae5:9:2",
        "astCommand": {
            "children": [
                {
                    "children": [
                        {
                            "children": [
                                {
                                    "children": [
                                        {
                                            "type": "ABS-PROBABLY-URL",
                                            "children": []
                                        }
                                    ],
                                    "type": "BASH-LITERAL"
                                }
                            ],
                            "type": "SC-PYTHON-ARG"
                        },
                        {
                            "children": [
                                {
                                    "children": [],
                                    "type": "BASH-LITERAL"
                                }
                            ],
                            "type": "SC-PYTHON-ARG"
                        },
                        {
                            "children": [
                                {
                                    "children": [],
                                    "type": "BASH-LITERAL"
                                }
                            ],
                            "type": "SC-PYTHON-ARG"
                        },
                        {
                            "children": [
                                {
                                    "children": [
                                        {
                                            "children": [],
                                            "type": "BASH-LITERAL"
                                        },
                                        {
                                            "children": [],
                                            "type": "BASH-VARIABLE:PYTHON_PIP_VERSION"
                                        }
                                    ],
                                    "type": "BASH-DOUBLE-QUOTED"
                                }
                            ],
                            "type": "SC-PYTHON-ARG"
                        }
                    ],
                    "type": "SC-PYTHON-ARGS"
                }
            ],
            "type": "SC-PYTHON"
        }
    },
    {
        "astCommandId": "027de8dd9fb86c52209cb18af272ab6958a5eae5:9:3",
        "astCommand": {
            "children": [
                {
                    "children": [],
                    "type": "SC-PIP-F-VERSION"
                }
            ],
            "type": "SC-PIP"
        }
    },
    {
        "astCommandId": "027de8dd9fb86c52209cb18af272ab6958a5eae5:9:4",
        "astCommand": {
            "children": [
                {
                    "children": [],
                    "type": "SC-RM-F-FORCE"
                },
                {
                    "children": [
                        {
                            "children": [
                                {
                                    "children": [
                                        {
                                            "type": "ABS-PROBABLY-URL",
                                            "children": []
                                        }
                                    ],
                                    "type": "BASH-LITERAL"
                                }
                            ],
                            "type": "SC-RM-PATH"
                        }
                    ],
                    "type": "SC-RM-PATHS"
                }
            ],
            "type": "SC-RM"
        }
    },
    {
        "astCommandId": "027de8dd9fb86c52209cb18af272ab6958a5eae5:10:0",
        "astCommand": {
            "children": [
                {
                    "children": [],
                    "type": "SC-PIP-F-NO-CACHE-DIR"
                },
                {
                    "children": [
                        {
                            "children": [
                                {
                                    "children": [],
                                    "type": "BASH-LITERAL"
                                }
                            ],
                            "type": "SC-PIP-TARGET"
                        }
                    ],
                    "type": "SC-PIP-TARGETS"
                }
            ],
            "type": "SC-PIP-INSTALL"
        }
    }
]